[
  {
    "id": 1,
    "condition": 4,
    "condition_param": [
      2
    ],
    "description": "CalabashDevelopCondition_1_Description",
    "reward_exp": [
      {
        "key": 10,
        "value": 10
      },
      {
        "key": 1,
        "value": 100
      }
    ]
  },
  {
    "id": 2,
    "condition": 4,
    "condition_param": [
      3
    ],
    "description": "CalabashDevelopCondition_2_Description",
    "reward_exp": [
      {
        "key": 10,
        "value": 10
      }
    ]
  },
  {
    "id": 3,
    "condition": 4,
    "condition_param": [
      4
    ],
    "description": "CalabashDevelopCondition_3_Description",
    "reward_exp": [
      {
        "key": 10,
        "value": 15
      }
    ]
  },
  {
    "id": 4,
    "condition": 4,
    "condition_param": [
      5
    ],
    "description": "CalabashDevelopCondition_4_Description",
    "reward_exp": [
      {
        "key": 10,
        "value": 20
      }
    ]
  },
  {
    "id": 5,
    "condition": 4,
    "condition_param": [
      2
    ],
    "description": "CalabashDevelopCondition_1_Description",
    "reward_exp": [
      {
        "key": 10,
        "value": 5
      }
    ]
  },
  {
    "id": 6,
    "condition": 4,
    "condition_param": [
      3
    ],
    "description": "CalabashDevelopCondition_2_Description",
    "reward_exp": [
      {
        "key": 10,
        "value": 5
      }
    ]
  },
  {
    "id": 7,
    "condition": 4,
    "condition_param": [
      4
    ],
    "description": "CalabashDevelopCondition_3_Description",
    "reward_exp": [
      {
        "key": 10,
        "value": 5
      }
    ]
  },
  {
    "id": 8,
    "condition": 4,
    "condition_param": [
      5
    ],
    "description": "CalabashDevelopCondition_4_Description",
    "reward_exp": [
      {
        "key": 10,
        "value": 5
      }
    ]
  }
]