[
  {
    "id": 1009,
    "view_name": "RogueShopView",
    "title": "NpcSystemBackground_1009_Title",
    "title_texture_path": "/Game/Aki/UI/UIResources/Common/Atlas/TabIcon/SP_IconRogueShop1.SP_IconRogueShop1",
    "title_bg_texture_path": "/Game/Aki/UI/UIResources/Common/Atlas/TabIcon/SP_BlackIconRogueShop.SP_BlackIconRogueShop",
    "title_symbol_color": "ed6a41",
    "caption_title": "",
    "caption_title_sprite_path": "",
    "cost_item_list": [
      80100000
    ],
    "is_help_button_visible": false,
    "help_group_id": 0
  }
]